odoo/addons/membership_delegated_partner/README.rst
odoo/addons/membership_delegated_partner/__init__.py
odoo/addons/membership_delegated_partner/__manifest__.py
odoo/addons/membership_delegated_partner/i18n/ar.po
odoo/addons/membership_delegated_partner/i18n/bg.po
odoo/addons/membership_delegated_partner/i18n/bs.po
odoo/addons/membership_delegated_partner/i18n/ca.po
odoo/addons/membership_delegated_partner/i18n/cs.po
odoo/addons/membership_delegated_partner/i18n/de.po
odoo/addons/membership_delegated_partner/i18n/el_GR.po
odoo/addons/membership_delegated_partner/i18n/en_GB.po
odoo/addons/membership_delegated_partner/i18n/es.po
odoo/addons/membership_delegated_partner/i18n/es_CR.po
odoo/addons/membership_delegated_partner/i18n/es_EC.po
odoo/addons/membership_delegated_partner/i18n/es_MX.po
odoo/addons/membership_delegated_partner/i18n/et.po
odoo/addons/membership_delegated_partner/i18n/fi.po
odoo/addons/membership_delegated_partner/i18n/fr.po
odoo/addons/membership_delegated_partner/i18n/fr_CA.po
odoo/addons/membership_delegated_partner/i18n/fr_CH.po
odoo/addons/membership_delegated_partner/i18n/gl.po
odoo/addons/membership_delegated_partner/i18n/hr.po
odoo/addons/membership_delegated_partner/i18n/hr_HR.po
odoo/addons/membership_delegated_partner/i18n/hu.po
odoo/addons/membership_delegated_partner/i18n/id.po
odoo/addons/membership_delegated_partner/i18n/it.po
odoo/addons/membership_delegated_partner/i18n/ja.po
odoo/addons/membership_delegated_partner/i18n/lt.po
odoo/addons/membership_delegated_partner/i18n/membership_delegated_partner.pot
odoo/addons/membership_delegated_partner/i18n/mk.po
odoo/addons/membership_delegated_partner/i18n/mn.po
odoo/addons/membership_delegated_partner/i18n/nb.po
odoo/addons/membership_delegated_partner/i18n/nb_NO.po
odoo/addons/membership_delegated_partner/i18n/nl.po
odoo/addons/membership_delegated_partner/i18n/nl_BE.po
odoo/addons/membership_delegated_partner/i18n/nl_NL.po
odoo/addons/membership_delegated_partner/i18n/pl.po
odoo13_addon_membership_delegated_partner-13.0.1.0.1.dev8.dist-info/METADATA
odoo13_addon_membership_delegated_partner-13.0.1.0.1.dev8.dist-info/WHEEL
odoo13_addon_membership_delegated_partner-13.0.1.0.1.dev8.dist-info/top_level.txt
odoo13_addon_membership_delegated_partner-13.0.1.0.1.dev8.dist-info/RECORD
